hydrapy/__init__.py
hydrapy/hydra.py
hydra_py-0.5.3.dist-info/LICENSE
hydra_py-0.5.3.dist-info/METADATA
hydra_py-0.5.3.dist-info/WHEEL
hydra_py-0.5.3.dist-info/top_level.txt
hydra_py-0.5.3.dist-info/RECORD
