Metadata-Version: 2.1
Name: hydra-py
Version: 0.5.3
Summary: Hydra for Python. A light-weight library for building distributed applications such as microservices.
Home-page: https://github.com/pnxtech/HydraPy
License: UNKNOWN
Platform: UNKNOWN
Classifier: Programming Language :: Python :: 3
Classifier: License :: OSI Approved :: MIT License
Classifier: Operating System :: OS Independent
Requires-Python: >=3.7
Requires-Dist: aioredis (==1.3.1)
Requires-Dist: psutil (==5.7.2)
Requires-Dist: shortuuid (==1.0.1)
